COAL-LAB/Cs221004_MID/Q3/Ques3.v
module gates(A,B,C,clk,reset,Z);

input A, B, C, clk, reset, result;
output Z;

wire A_or_B_and_C;
 
assign A_or_B_and_C = (A | B) & C;

reg Z;
assign result = A_or_B_and_C;

always @(posedge clk)begin
  if(reset==1'b1)begin
    // result <= 1'b0;
    Z <= 1'b0;
  end
  else begin
    // result <= A_or_B_and_C;
    Z <= result;
  end
end

// assign Z = result;

endmodule

COAL-LAB/Cs221004_MID/Q3/Ques3_TestBench.v
module tb();

reg A, B, C, clk, reset;
wire Z;

gates dut(
    .A(A),
    .B(B),
    .C(C),
    .clk(clk),
    .reset(reset),
    .Z(Z)
);

always begin
  clk<=1'b1;
  #50;
  clk<=1'b0;
  #50;
end

initial begin
  reset<=1'b1;
  #100;
  reset<=1'b0;
  #100;

  A<=1'b0;
  B<=1'b0;
  C<=1'b0;
  #25
   A<=1'b0;
  B<=1'b0;
  C<=1'b1;
  #25
   A<=1'b0;
  B<=1'b1;
  C<=1'b0;
  #25
   A<=1'b0;
  B<=1'b1;
  C<=1'b1;
  #25
   A<=1'b1;
  B<=1'b0;
  C<=1'b0;
  #25
   A<=1'b1;
  B<=1'b0;
  C<=1'b1;
  #25
   A<=1'b1;
  B<=1'b1;
  C<=1'b0;
  #25
   A<=1'b1;
  B<=1'b1;
  C<=1'b1;
  #25
  
  $finish;
end

initial begin
  $dumpfile("dumpQues3.vcd");
  $dumpvars(0);
end


endmodule

COAL-LAB/Cs221004_MID/Q3/dumpQues3.vcd
$date
	Tue Dec 19 12:04:37 2023
$end
$version
	Icarus Verilog
$end
$timescale
	1s
$end
$scope module tb $end
$var wire 1 ! Z $end
$var reg 1 " A $end
$var reg 1 # B $end
$var reg 1 $ C $end
$var reg 1 % clk $end
$var reg 1 & reset $end
$scope module dut $end
$var wire 1 " A $end
$var wire 1 ' A_or_B_and_C $end
$var wire 1 # B $end
$var wire 1 $ C $end
$var wire 1 % clk $end
$var wire 1 & reset $end
$var wire 1 ( result $end
$var reg 1 ! Z $end
$upscope $end
$upscope $end
$enddefinitions $end
$comment Show the parameter values. $end
$dumpall
$end
#0
$dumpvars
x(
x'
1&
1%
x$
x#
x"
0!
$end
#50
0%
#100
x!
1%
0&
#150
0%
#200
0!
0(
0'
1%
0$
0#
0"
#225
1$
#250
0$
1#
0%
#275
1(
1'
1$
#300
1!
0(
0'
0$
0#
1"
1%
#325
1(
1'
1$
#350
0(
0'
0$
1#
0%
#375
1(
1'
1$
