COAL-LAB/Cs221004_MID/Q2/Ques2.v
module gate (Q,P,R,F);
input Q, P,R;
output F;

wire Q_or_P;
wire P_or_R;
wire Q_or_P_AND_P_or_R;

assign Q_or_P = Q|P;
assign P_or_R = P|R;
assign  Q_or_P_AND_P_or_R = (Q_or_P)&(P_or_R);
assign F = Q_or_P_AND_P_or_R;



endmodule

COAL-LAB/Cs221004_MID/Q2/Ques2_TestBench.v
module tb;
reg P,Q,R;
wire F;
gate dut(
    .P(P),
    .Q(Q),
    .R(R),
    .F(F)
);
 initial begin 
P<=1'b0;
  Q<=1'b0;
  R<=1'b0;
  #25
   P<=1'b0;
  Q<=1'b0;
  R<=1'b1;
  #25
   P<=1'b0;
  Q<=1'b1;
  R<=1'b0;
  #25
   P<=1'b0;
  Q<=1'b1;
  R<=1'b1;
  #25
   P<=1'b1;
  Q<=1'b0;
  R<=1'b0;
  #25
   P<=1'b1;
  Q<=1'b0;
  R<=1'b1;
  #25
   P<=1'b1;
  Q<=1'b1;
  R<=1'b0;
  #25
   P<=1'b1;
  Q<=1'b1;
  R<=1'b1;
  
  
  $finish;

end
initial begin 
         $dumpfile("dumpQues2.vcd");
         $dumpvars(0);
         end
endmodule

COAL-LAB/Cs221004_MID/Q2/dumpQues2.vcd
$date
	Tue Dec 19 12:24:16 2023
$end
$version
	Icarus Verilog
$end
$timescale
	1s
$end
$scope module tb $end
$var wire 1 ! F $end
$var reg 1 " P $end
$var reg 1 # Q $end
$var reg 1 $ R $end
$scope module dut $end
$var wire 1 ! F $end
$var wire 1 " P $end
$var wire 1 % P_or_R $end
$var wire 1 # Q $end
$var wire 1 & Q_or_P $end
$var wire 1 ' Q_or_P_AND_P_or_R $end
$var wire 1 $ R $end
$upscope $end
$upscope $end
$enddefinitions $end
$comment Show the parameter values. $end
$dumpall
$end
#0
$dumpvars
0'
0&
0%
0$
0#
0"
0!
$end
#25
1%
1$
#50
0%
1&
0$
1#
#75
1!
1'
1%
1$
#100
0$
0#
1"
#125
1$
#150
0$
1#
#175
1$
